README.md
setup.py
nobug/Jesus.py
nobug/__init__.py
nobug/awesome_caonima.py
nobug/book.py
nobug/buddha.py
nobug/caonima.py
nobug/lying_buddha.py
nobug/success.py
nobug.egg-info/PKG-INFO
nobug.egg-info/SOURCES.txt
nobug.egg-info/dependency_links.txt
nobug.egg-info/top_level.txt