Metadata-Version: 1.0
Name: nobug
Version: 0.3.0
Summary: b'no bug no bug'
Home-page: https://github.com/IanSmith123/nobug
Author: Les1ie
Author-email: iansmith@qq.com
License: UNKNOWN
Platform: UNKNOWN
